hack4u/__init__.py
hack4u/courses.py
hack4u/utils.py
Haack4uu-3.1.8.dist-info/METADATA
Haack4uu-3.1.8.dist-info/WHEEL
Haack4uu-3.1.8.dist-info/top_level.txt
Haack4uu-3.1.8.dist-info/RECORD
