Metadata-Version: 2.1
Name: Haack4uu
Version: 3.1.8
Summary: Biblioteca para practicar.
Home-page: https://hack4u.io
Author: CP
